{
  "tag": "2025-05-18_113429",
  "event": {
    "event_type": "touch",
    "log_lines": null,
    "x": null,
    "y": null,
    "view": {
      "package": "com.microsoft.translator",
      "visible": true,
      "checkable": false,
      "child_count": 0,
      "editable": false,
      "clickable": false,
      "is_password": false,
      "focusable": false,
      "enabled": true,
      "content_description": null,
      "children": [],
      "focused": false,
      "bounds": [
        [
          42,
          740
        ],
        [
          1038,
          977
        ]
      ],
      "resource_id": "com.microsoft.translator:id/privacy_details",
      "checked": false,
      "text": "Translator is powered by machine learning and the image, voice and text information you provide for translation will be used to improve Microsoft products and services. We protect your privacy by taking steps to de-identify your data and keep it secure.",
      "class": "android.widget.TextView",
      "scrollable": false,
      "selected": false,
      "long_clickable": false,
      "parent": 10,
      "temp_id": 11,
      "size": "996*237",
      "signature": "[class]android.widget.TextView[resource_id]com.microsoft.translator:id/privacy_details[text]None[enabled,,]",
      "view_str": "0f3d198b278e3be1733d5ce9276e6f86",
      "allowed_actions": [
        "touch"
      ],
      "special_attrs": [],
      "local_id": "2",
      "desc": "<p bound_box=42,740,1038,977>Translator is powered by machine learning and the image, voice and text information you provide for translation will be used to improve Microsoft products and services. We protect your privacy by taking steps to de-identify your data and keep it secure.</p>"
    }
  },
  "start_state": "43ea0db9f7d5f52260859760bc2d5827",
  "stop_state": "43ea0db9f7d5f52260859760bc2d5827",
  "event_str": "TouchEvent(state=43ea0db9f7d5f52260859760bc2d5827, view=0f3d198b278e3be1733d5ce9276e6f86(LandingActivity/TextView-Translator))"
}