{
  "tag": "2025-05-18_153131",
  "state_str": "caabf957407f9755dd5c0512bbdcea15",
  "state_str_content_free": "bab5a09ed2ed64fe52321e738be0f3ae",
  "foreground_activity": "com.traveloka.android/.user.onboarding.OnBoardingActivity",
  "activity_stack": [
    "com.traveloka.android/.user.onboarding.OnBoardingActivity"
  ],
  "background_services": [
    "com.google.android.gms/.nearby.presence.service.LifeCycleService",
    "com.google.android.gms/.play.integrity.api.service.IntegrityApiPersistentService",
    "com.google.android.gms/.ads.identifier.service.AdvertisingIdService",
    "com.google.android.apps.messaging/com.google.android.ims.service.JibeService",
    "com.google.android.networkstack.tethering/com.android.networkstack.tethering.TetheringService",
    "com.google.android.ext.services/com.android.textclassifier.DefaultTextClassifierService",
    "com.google.android.gms/.nearby.sharing.ReceiveSurfaceService",
    "com.android.systemui/.keyguard.KeyguardService",
    "com.android.bluetooth/.btservice.AdapterService",
    "com.google.android.gms/org.chromium.content.app.SandboxedProcessService0",
    "com.google.android.webview/org.chromium.android_webview.services.MetricsBridgeService",
    "com.android.systemui/.ImageWallpaper",
    "com.google.android.setupwizard/.notification.SetupNotificationService",
    "com.google.android.gms/.personalsafety.service.SndDetectionService",
    "com.google.android.gms/.auth.setup.devicesignals.LockScreenService",
    "com.google.android.gms/.gcm.GcmService",
    "com.google.android.gms/.chimera.PersistentApiServiceNoInstantApps",
    "com.google.android.gms/.clearcut.debug.ClearcutDebugDumpService",
    "com.google.android.apps.messaging/com.google.android.ims.binding.SystemBindingService",
    "com.google.android.gms/.chimera.PersistentApiService",
    "com.google.android.gms/.location.geocode.GeocodeService",
    "com.android.phone/com.android.internal.telephony.CellularNetworkService",
    "com.google.android.gms/.magictether.service.TetherService",
    "com.google.android.gms/.chimera.PersistentBoundBrokerService",
    "com.android.bluetooth/.gatt.GattService",
    "com.google.android.gms/.chimera.GmsBoundBrokerService",
    "com.google.android.gms/.chimera.GmsApiService",
    "com.google.android.gms/.findmydevice.spot.bleadvertising.OfflineBeaconService_Persistent",
    "com.google.android.gms/.tron.CollectionService",
    "com.google.android.googlequicksearchbox/com.google.android.apps.gsa.nowoverlayservice.DrawerOverlayService",
    "com.google.android.gms/.nearby.sharing.SendSurfaceService",
    "io.github.ylimit.droidbotapp/.DroidBotIME",
    "com.android.bluetooth/.pbap.BluetoothPbapService",
    "com.google.android.gms/com.google.android.location.fused.FusedLocationService",
    "com.google.android.gms/.gcm.nts.SchedulerService",
    "com.google.android.ext.services/android.ext.services.autofill.InlineSuggestionRenderServiceImpl",
    "com.google.android.setupwizard/.logging.ScreenOnClock",
    "com.android.bluetooth/.a2dp.A2dpService",
    "com.google.android.providers.media.module/com.android.providers.media.fuse.ExternalStorageServiceImpl",
    "io.github.ylimit.droidbotapp/io.github.privacystreams.accessibility.PSAccessibilityService",
    "com.google.android.googlequicksearchbox/com.google.android.apps.gsa.nga.engine.viss.NgaService",
    "com.google.android.gms/.thunderbird.EmergencyPersistentService",
    "com.google.android.apps.nexuslauncher/com.android.launcher3.notification.NotificationListener",
    "com.android.systemui/.SystemUIService",
    "com.google.android.googlequicksearchbox/com.google.frameworks.client.data.android.server.tiktok.InteractorProcessEndpointService",
    "android/.hardware.location.GeofenceHardwareService",
    "com.android.se/.SecureElementService",
    "com.google.android.gms/.chimera.PersistentDirectBootAwareApiService",
    "com.google.android.gms/.chimera.PersistentIntentOperationService",
    "com.android.bluetooth/.hid.HidDeviceService",
    "com.google.android.gms/.geotimezone.GeoTimeZoneService",
    "com.google.android.gms/.location.persistent.LocationPersistentService",
    "com.google.android.gms/.nearby.discovery.service.DiscoveryService",
    "com.google.android.gms/com.google.android.location.internal.PendingIntentCallbackService",
    "com.google.android.gms/.fido.authenticator.service.AuthenticatorService",
    "com.google.android.apps.photos/com.google.android.libraries.social.async.BackgroundTaskJobService",
    "com.google.android.gms/com.google.android.location.internal.server.GoogleLocationService",
    "com.google.android.gms/com.google.android.contextmanager.service.ContextManagerService",
    "com.android.systemui/.dump.SystemUIAuxiliaryDumpService",
    "com.google.android.gms/com.google.android.location.network.NetworkLocationService",
    "com.android.stk/.StkAppService",
    "com.google.android.gms/com.google.android.location.internal.GoogleLocationManagerService",
    "com.android.phone/com.android.internal.telephony.dataconnection.CellularDataService",
    "com.android.server.telecom/.components.TelecomService",
    "com.google.android.networkstack/com.android.server.NetworkStackService",
    "com.traveloka.android/.framework.interprocess.service.TvlkFcmListenerService",
    "com.android.bluetooth/.hfp.HeadsetService",
    "com.google.android.googlequicksearchbox/com.google.android.voiceinteraction.GsaVoiceInteractionService",
    "com.android.emulator.multidisplay/.MultiDisplayService",
    "com.google.android.gms/.crisisalerts.init.CrisisAlertsPersistentService",
    "com.android.phone/.vvm.RemoteVvmTaskManager",
    "com.google.android.setupwizard/.predeferred.PreDeferredUpdateService",
    "com.android.ons/.OpportunisticNetworkService",
    "com.google.android.gms/.common.stats.GmsCoreStatsService",
    "com.google.android.gms/com.google.android.location.internal.server.HardwareArProviderService",
    "com.google.android.gms/.dtdi.lifecycle.LifecycleService",
    "com.google.android.gms/.chimera.GmsInternalBoundBrokerService",
    "com.traveloka.android/com.google.android.gms.tagmanager.TagManagerService",
    "com.android.vending/com.google.android.finsky.externalreferrer.GetInstallReferrerService",
    "com.android.bluetooth/.map.BluetoothMapService",
    "com.android.phone/com.android.services.telephony.sip.components.TelephonySipService",
    "com.google.android.gms/.personalsafety.service.PersonalSafetyService",
    "com.android.phone/.TelephonyDebugService",
    "com.android.bluetooth/.hid.HidHostService",
    "com.google.android.googlequicksearchbox/com.google.android.libraries.notifications.platform.entrypoints.firebase.FirebaseMessagingServiceImpl",
    "com.android.bluetooth/.opp.BluetoothOppService",
    "com.android.bluetooth/.pan.PanService",
    "com.android.bluetooth/.avrcp.AvrcpTargetService",
    "com.google.android.apps.nexuslauncher/com.android.quickstep.TouchInteractionService",
    "com.google.android.cellbroadcastservice/com.android.cellbroadcastservice.DefaultCellBroadcastService"
  ],
  "width": 1080,
  "height": 2400,
  "views": [
    {
      "package": "com.traveloka.android",
      "visible": true,
      "checkable": false,
      "child_count": 2,
      "editable": false,
      "clickable": false,
      "is_password": false,
      "focusable": false,
      "enabled": true,
      "content_description": null,
      "children": [
        1,
        44
      ],
      "focused": false,
      "bounds": [
        [
          0,
          0
        ],
        [
          1080,
          2400
        ]
      ],
      "resource_id": null,
      "checked": false,
      "text": null,
      "class": "android.widget.FrameLayout",
      "scrollable": false,
      "selected": false,
      "long_clickable": false,
      "parent": -1,
      "temp_id": 0,
      "size": "1080*2400",
      "signature": "[class]android.widget.FrameLayout[resource_id]None[text]None[enabled,,]",
      "view_str": "546fd43f917dceaeba7095074a54d82c"
    },
    {
      "package": "com.traveloka.android",
      "visible": true,
      "checkable": false,
      "child_count": 1,
      "editable": false,
      "clickable": false,
      "is_password": false,
      "focusable": false,
      "enabled": true,
      "content_description": null,
      "children": [
        2
      ],
      "focused": false,
      "bounds": [
        [
          0,
          0
        ],
        [
          1080,
          2274
        ]
      ],
      "resource_id": null,
      "checked": false,
      "text": null,
      "class": "android.widget.LinearLayout",
      "scrollable": false,
      "selected": false,
      "long_clickable": false,
      "parent": 0,
      "temp_id": 1,
      "size": "1080*2274",
      "signature": "[class]android.widget.LinearLayout[resource_id]None[text]None[enabled,,]",
      "view_str": "81e51667c306a7bf34e776f031cca4f9"
    },
    {
      "package": "com.traveloka.android",
      "visible": true,
      "checkable": false,
      "child_count": 1,
      "editable": false,
      "clickable": false,
      "is_password": false,
      "focusable": false,
      "enabled": true,
      "content_description": null,
      "children": [
        3
      ],
      "focused": false,
      "bounds": [
        [
          0,
          0
        ],
        [
          1080,
          2274
        ]
      ],
      "resource_id": null,
      "checked": false,
      "text": null,
      "class": "android.widget.FrameLayout",
      "scrollable": false,
      "selected": false,
      "long_clickable": false,
      "parent": 1,
      "temp_id": 2,
      "size": "1080*2274",
      "signature": "[class]android.widget.FrameLayout[resource_id]None[text]None[enabled,,]",
      "view_str": "68965cb755132a8a1c602ed4426cfaa8"
    },
    {
      "package": "com.traveloka.android",
      "visible": true,
      "checkable": false,
      "child_count": 1,
      "editable": false,
      "clickable": false,
      "is_password": false,
      "focusable": false,
      "enabled": true,
      "content_description": null,
      "children": [
        4
      ],
      "focused": false,
      "bounds": [
        [
          0,
          0
        ],
        [
          1080,
          2274
        ]
      ],
      "resource_id": "com.traveloka.android:id/action_bar_root",
      "checked": false,
      "text": null,
      "class": "android.widget.FrameLayout",
      "scrollable": false,
      "selected": false,
      "long_clickable": false,
      "parent": 2,
      "temp_id": 3,
      "size": "1080*2274",
      "signature": "[class]android.widget.FrameLayout[resource_id]com.traveloka.android:id/action_bar_root[text]None[enabled,,]",
      "view_str": "47f10314360d6e81ff59b932c722cda6"
    },
    {
      "package": "com.traveloka.android",
      "visible": true,
      "checkable": false,
      "child_count": 1,
      "editable": false,
      "clickable": false,
      "is_password": false,
      "focusable": false,
      "enabled": true,
      "content_description": null,
      "children": [
        5
      ],
      "focused": false,
      "bounds": [
        [
          0,
          0
        ],
        [
          1080,
          2274
        ]
      ],
      "resource_id": "android:id/content",
      "checked": false,
      "text": null,
      "class": "android.widget.FrameLayout",
      "scrollable": false,
      "selected": false,
      "long_clickable": false,
      "parent": 3,
      "temp_id": 4,
      "size": "1080*2274",
      "signature": "[class]android.widget.FrameLayout[resource_id]android:id/content[text]None[enabled,,]",
      "view_str": "03bc88b088e1efb3d3755f3e29ed2c6a"
    },
    {
      "package": "com.traveloka.android",
      "visible": true,
      "checkable": false,
      "child_count": 2,
      "editable": false,
      "clickable": false,
      "is_password": false,
      "focusable": false,
      "enabled": true,
      "content_description": null,
      "children": [
        6,
        7
      ],
      "focused": false,
      "bounds": [
        [
          0,
          0
        ],
        [
          1080,
          2274
        ]
      ],
      "resource_id": "com.traveloka.android:id/core_coordinator_layout",
      "checked": false,
      "text": null,
      "class": "android.view.ViewGroup",
      "scrollable": false,
      "selected": false,
      "long_clickable": false,
      "parent": 4,
      "temp_id": 5,
      "size": "1080*2274",
      "signature": "[class]android.view.ViewGroup[resource_id]com.traveloka.android:id/core_coordinator_layout[text]None[enabled,,]",
      "view_str": "1109c5eadf077ffc408ef62460a41d86"
    },
    {
      "package": "com.traveloka.android",
      "visible": false,
      "checkable": false,
      "child_count": 0,
      "editable": false,
      "clickable": false,
      "is_password": false,
      "focusable": false,
      "enabled": true,
      "content_description": null,
      "children": [],
      "focused": false,
      "bounds": [
        [
          0,
          0
        ],
        [
          1080,
          0
        ]
      ],
      "resource_id": "com.traveloka.android:id/core_app_bar",
      "checked": false,
      "text": null,
      "class": "android.widget.LinearLayout",
      "scrollable": false,
      "selected": false,
      "long_clickable": false,
      "parent": 5,
      "temp_id": 6,
      "size": "1080*0",
      "signature": "[class]android.widget.LinearLayout[resource_id]com.traveloka.android:id/core_app_bar[text]None[enabled,,]",
      "view_str": "19b5232cd63e864b8f8abc80ce494099"
    },
    {
      "package": "com.traveloka.android",
      "visible": true,
      "checkable": false,
      "child_count": 1,
      "editable": false,
      "clickable": false,
      "is_password": false,
      "focusable": false,
      "enabled": true,
      "content_description": null,
      "children": [
        8
      ],
      "focused": false,
      "bounds": [
        [
          0,
          0
        ],
        [
          1080,
          2274
        ]
      ],
      "resource_id": "com.traveloka.android:id/core_content_layout",
      "checked": false,
      "text": null,
      "class": "android.widget.FrameLayout",
      "scrollable": false,
      "selected": false,
      "long_clickable": false,
      "parent": 5,
      "temp_id": 7,
      "size": "1080*2274",
      "signature": "[class]android.widget.FrameLayout[resource_id]com.traveloka.android:id/core_content_layout[text]None[enabled,,]",
      "view_str": "f702991dc1a4fca6e5f9b8aa71509cfa"
    },
    {
      "package": "com.traveloka.android",
      "visible": true,
      "checkable": false,
      "child_count": 2,
      "editable": false,
      "clickable": false,
      "is_password": false,
      "focusable": false,
      "enabled": true,
      "content_description": null,
      "children": [
        9,
        37
      ],
      "focused": false,
      "bounds": [
        [
          0,
          0
        ],
        [
          1080,
          2274
        ]
      ],
      "resource_id": null,
      "checked": false,
      "text": null,
      "class": "android.widget.FrameLayout",
      "scrollable": false,
      "selected": false,
      "long_clickable": false,
      "parent": 7,
      "temp_id": 8,
      "size": "1080*2274",
      "signature": "[class]android.widget.FrameLayout[resource_id]None[text]None[enabled,,]",
      "view_str": "930d3f8ce34fefd88b6ab679070c87f6"
    },
    {
      "package": "com.traveloka.android",
      "visible": true,
      "checkable": false,
      "child_count": 2,
      "editable": false,
      "clickable": false,
      "is_password": false,
      "focusable": false,
      "enabled": true,
      "content_description": null,
      "children": [
        10,
        31
      ],
      "focused": false,
      "bounds": [
        [
          0,
          0
        ],
        [
          1080,
          2274
        ]
      ],
      "resource_id": "com.traveloka.android:id/container",
      "checked": false,
      "text": null,
      "class": "android.widget.LinearLayout",
      "scrollable": false,
      "selected": false,
      "long_clickable": false,
      "parent": 8,
      "temp_id": 9,
      "size": "1080*2274",
      "signature": "[class]android.widget.LinearLayout[resource_id]com.traveloka.android:id/container[text]None[enabled,,]",
      "view_str": "aa63d28587289eb01b1419daa49474ef"
    },
    {
      "package": "com.traveloka.android",
      "visible": true,
      "checkable": false,
      "child_count": 1,
      "editable": false,
      "clickable": false,
      "is_password": false,
      "focusable": false,
      "enabled": true,
      "content_description": null,
      "children": [
        11
      ],
      "focused": false,
      "bounds": [
        [
          0,
          0
        ],
        [
          1080,
          2274
        ]
      ],
      "resource_id": "com.traveloka.android:id/dynamic_locale_widget",
      "checked": false,
      "text": null,
      "class": "android.widget.FrameLayout",
      "scrollable": false,
      "selected": false,
      "long_clickable": false,
      "parent": 9,
      "temp_id": 10,
      "size": "1080*2274",
      "signature": "[class]android.widget.FrameLayout[resource_id]com.traveloka.android:id/dynamic_locale_widget[text]None[enabled,,]",
      "view_str": "097bfbc9bcdd248d03bdfd21162faf69"
    },
    {
      "package": "com.traveloka.android",
      "visible": true,
      "checkable": false,
      "child_count": 2,
      "editable": false,
      "clickable": false,
      "is_password": false,
      "focusable": false,
      "enabled": true,
      "content_description": null,
      "children": [
        12,
        28
      ],
      "focused": false,
      "bounds": [
        [
          0,
          0
        ],
        [
          1080,
          2274
        ]
      ],
      "resource_id": "com.traveloka.android:id/layout_country_selection",
      "checked": false,
      "text": null,
      "class": "android.widget.RelativeLayout",
      "scrollable": false,
      "selected": false,
      "long_clickable": false,
      "parent": 10,
      "temp_id": 11,
      "size": "1080*2274",
      "signature": "[class]android.widget.RelativeLayout[resource_id]com.traveloka.android:id/layout_country_selection[text]None[enabled,,]",
      "view_str": "ed9c7fa350d67ce927633524faa8332c"
    },
    {
      "package": "com.traveloka.android",
      "visible": true,
      "checkable": false,
      "child_count": 1,
      "editable": false,
      "clickable": false,
      "is_password": false,
      "focusable": true,
      "enabled": true,
      "content_description": null,
      "children": [
        13
      ],
      "focused": false,
      "bounds": [
        [
          0,
          0
        ],
        [
          1080,
          2085
        ]
      ],
      "resource_id": "com.traveloka.android:id/scroll_view",
      "checked": false,
      "text": null,
      "class": "android.widget.ScrollView",
      "scrollable": false,
      "selected": false,
      "long_clickable": false,
      "parent": 11,
      "temp_id": 12,
      "size": "1080*2085",
      "signature": "[class]android.widget.ScrollView[resource_id]com.traveloka.android:id/scroll_view[text]None[enabled,,]",
      "view_str": "29d6ba23ca4fb23f491fece7f3f3b305"
    },
    {
      "package": "com.traveloka.android",
      "visible": true,
      "checkable": false,
      "child_count": 2,
      "editable": false,
      "clickable": false,
      "is_password": false,
      "focusable": false,
      "enabled": true,
      "content_description": null,
      "children": [
        14,
        15
      ],
      "focused": false,
      "bounds": [
        [
          0,
          0
        ],
        [
          1080,
          1232
        ]
      ],
      "resource_id": null,
      "checked": false,
      "text": null,
      "class": "android.widget.LinearLayout",
      "scrollable": false,
      "selected": false,
      "long_clickable": false,
      "parent": 12,
      "temp_id": 13,
      "size": "1080*1232",
      "signature": "[class]android.widget.LinearLayout[resource_id]None[text]None[enabled,,]",
      "view_str": "dcad9122ea7a9c1bb21407fa07bc413b"
    },
    {
      "package": "com.traveloka.android",
      "visible": true,
      "checkable": false,
      "child_count": 0,
      "editable": false,
      "clickable": false,
      "is_password": false,
      "focusable": false,
      "enabled": true,
      "content_description": null,
      "children": [],
      "focused": false,
      "bounds": [
        [
          435,
          158
        ],
        [
          645,
          368
        ]
      ],
      "resource_id": null,
      "checked": false,
      "text": null,
      "class": "android.widget.ImageView",
      "scrollable": false,
      "selected": false,
      "long_clickable": false,
      "parent": 13,
      "temp_id": 14,
      "size": "210*210",
      "signature": "[class]android.widget.ImageView[resource_id]None[text]None[enabled,,]",
      "view_str": "414aed706b4f5763bff100843ac1e754"
    },
    {
      "package": "com.traveloka.android",
      "visible": true,
      "checkable": false,
      "child_count": 4,
      "editable": false,
      "clickable": false,
      "is_password": false,
      "focusable": false,
      "enabled": true,
      "content_description": null,
      "children": [
        16,
        17,
        18,
        23
      ],
      "focused": false,
      "bounds": [
        [
          42,
          473
        ],
        [
          1038,
          1190
        ]
      ],
      "resource_id": "com.traveloka.android:id/layout_content",
      "checked": false,
      "text": null,
      "class": "android.widget.LinearLayout",
      "scrollable": false,
      "selected": false,
      "long_clickable": false,
      "parent": 13,
      "temp_id": 15,
      "size": "996*717",
      "signature": "[class]android.widget.LinearLayout[resource_id]com.traveloka.android:id/layout_content[text]None[enabled,,]",
      "view_str": "b060b293fc06c61f5829daa88a50501b"
    },
    {
      "package": "com.traveloka.android",
      "visible": true,
      "checkable": false,
      "child_count": 0,
      "editable": false,
      "clickable": false,
      "is_password": false,
      "focusable": false,
      "enabled": true,
      "content_description": null,
      "children": [],
      "focused": false,
      "bounds": [
        [
          42,
          473
        ],
        [
          1038,
          530
        ]
      ],
      "resource_id": "com.traveloka.android:id/on_board_title",
      "checked": false,
      "text": "Hello! Welcome to Traveloka.",
      "class": "android.widget.TextView",
      "scrollable": false,
      "selected": false,
      "long_clickable": false,
      "parent": 15,
      "temp_id": 16,
      "size": "996*57",
      "signature": "[class]android.widget.TextView[resource_id]com.traveloka.android:id/on_board_title[text]Hello! Welcome to Traveloka.[enabled,,]",
      "view_str": "df3f773991bbc9a713672e28763651b5",
      "allowed_actions": [
        "touch"
      ],
      "special_attrs": [],
      "local_id": "0",
      "desc": "<p bound_box=42,473,1038,530>Hello! Welcome to Traveloka.</p>"
    },
    {
      "package": "com.traveloka.android",
      "visible": true,
      "checkable": false,
      "child_count": 0,
      "editable": false,
      "clickable": false,
      "is_password": false,
      "focusable": false,
      "enabled": true,
      "content_description": null,
      "children": [],
      "focused": false,
      "bounds": [
        [
          42,
          572
        ],
        [
          1038,
          623
        ]
      ],
      "resource_id": "com.traveloka.android:id/on_board_description",
      "checked": false,
      "text": "To continue, pick your country and language.",
      "class": "android.widget.TextView",
      "scrollable": false,
      "selected": false,
      "long_clickable": false,
      "parent": 15,
      "temp_id": 17,
      "size": "996*51",
      "signature": "[class]android.widget.TextView[resource_id]com.traveloka.android:id/on_board_description[text]To continue, pick your country and language.[enabled,,]",
      "view_str": "72ec929f8cba673b548762848144a9c3",
      "allowed_actions": [
        "touch"
      ],
      "special_attrs": [],
      "local_id": "1",
      "desc": "<p bound_box=42,572,1038,623>To continue, pick your country and language.</p>"
    },
    {
      "package": "com.traveloka.android",
      "visible": true,
      "checkable": false,
      "child_count": 3,
      "editable": false,
      "clickable": false,
      "is_password": false,
      "focusable": false,
      "enabled": true,
      "content_description": null,
      "children": [
        19,
        20,
        22
      ],
      "focused": false,
      "bounds": [
        [
          42,
          707
        ],
        [
          1038,
          917
        ]
      ],
      "resource_id": "com.traveloka.android:id/input_country",
      "checked": false,
      "text": null,
      "class": "android.view.ViewGroup",
      "scrollable": false,
      "selected": false,
      "long_clickable": false,
      "parent": 15,
      "temp_id": 18,
      "size": "996*210",
      "signature": "[class]android.view.ViewGroup[resource_id]com.traveloka.android:id/input_country[text]None[enabled,,]",
      "view_str": "d686ca9a712629a8162f4dd85e5b4a6e"
    },
    {
      "package": "com.traveloka.android",
      "visible": true,
      "checkable": false,
      "child_count": 0,
      "editable": false,
      "clickable": false,
      "is_password": false,
      "focusable": false,
      "enabled": true,
      "content_description": null,
      "children": [],
      "focused": false,
      "bounds": [
        [
          42,
          725
        ],
        [
          1038,
          797
        ]
      ],
      "resource_id": "com.traveloka.android:id/label_text_view",
      "checked": false,
      "text": "Your Location",
      "class": "android.widget.TextView",
      "scrollable": false,
      "selected": false,
      "long_clickable": false,
      "parent": 18,
      "temp_id": 19,
      "size": "996*72",
      "signature": "[class]android.widget.TextView[resource_id]com.traveloka.android:id/label_text_view[text]Your Location[enabled,,]",
      "view_str": "ae817c74425347850b32cf836dfc764c",
      "allowed_actions": [
        "touch"
      ],
      "special_attrs": [],
      "local_id": "2",
      "desc": "<p bound_box=42,725,1038,797>Your Location</p>"
    },
    {
      "package": "com.traveloka.android",
      "visible": true,
      "checkable": false,
      "child_count": 1,
      "editable": false,
      "clickable": false,
      "is_password": false,
      "focusable": false,
      "enabled": true,
      "content_description": null,
      "children": [
        21
      ],
      "focused": false,
      "bounds": [
        [
          42,
          791
        ],
        [
          1038,
          896
        ]
      ],
      "resource_id": "com.traveloka.android:id/widget_view",
      "checked": false,
      "text": null,
      "class": "android.widget.FrameLayout",
      "scrollable": false,
      "selected": false,
      "long_clickable": false,
      "parent": 18,
      "temp_id": 20,
      "size": "996*105",
      "signature": "[class]android.widget.FrameLayout[resource_id]com.traveloka.android:id/widget_view[text]None[enabled,,]",
      "view_str": "28e1aca75823d9efcab47eda3bd2b522"
    },
    {
      "package": "com.traveloka.android",
      "visible": true,
      "checkable": false,
      "child_count": 0,
      "editable": true,
      "clickable": true,
      "is_password": false,
      "focusable": true,
      "enabled": true,
      "content_description": null,
      "children": [],
      "focused": false,
      "bounds": [
        [
          42,
          791
        ],
        [
          1038,
          896
        ]
      ],
      "resource_id": "com.traveloka.android:id/edit_text_field",
      "checked": false,
      "text": "Global",
      "class": "android.widget.EditText",
      "scrollable": false,
      "selected": false,
      "long_clickable": true,
      "parent": 20,
      "temp_id": 21,
      "size": "996*105",
      "signature": "[class]android.widget.EditText[resource_id]com.traveloka.android:id/edit_text_field[text]Global[enabled,,]",
      "view_str": "441419a6cb2c26ac4dbf75d03666e56e",
      "allowed_actions": [
        "touch",
        "set_text",
        "long_touch"
      ],
      "special_attrs": [],
      "local_id": "3",
      "desc": "<input bound_box=42,791,1038,896>Global</input>"
    },
    {
      "package": "com.traveloka.android",
      "visible": true,
      "checkable": false,
      "child_count": 0,
      "editable": false,
      "clickable": false,
      "is_password": false,
      "focusable": false,
      "enabled": true,
      "content_description": null,
      "children": [],
      "focused": false,
      "bounds": [
        [
          975,
          823
        ],
        [
          1017,
          865
        ]
      ],
      "resource_id": "com.traveloka.android:id/icon_end_view",
      "checked": false,
      "text": null,
      "class": "android.widget.ImageView",
      "scrollable": false,
      "selected": false,
      "long_clickable": false,
      "parent": 18,
      "temp_id": 22,
      "size": "42*42",
      "signature": "[class]android.widget.ImageView[resource_id]com.traveloka.android:id/icon_end_view[text]None[enabled,,]",
      "view_str": "6fbb8024b8cdd337e183d87dbfa12e64"
    },
    {
      "package": "com.traveloka.android",
      "visible": true,
      "checkable": false,
      "child_count": 3,
      "editable": false,
      "clickable": false,
      "is_password": false,
      "focusable": false,
      "enabled": true,
      "content_description": null,
      "children": [
        24,
        25,
        27
      ],
      "focused": false,
      "bounds": [
        [
          42,
          980
        ],
        [
          1038,
          1190
        ]
      ],
      "resource_id": "com.traveloka.android:id/input_language",
      "checked": false,
      "text": null,
      "class": "android.view.ViewGroup",
      "scrollable": false,
      "selected": false,
      "long_clickable": false,
      "parent": 15,
      "temp_id": 23,
      "size": "996*210",
      "signature": "[class]android.view.ViewGroup[resource_id]com.traveloka.android:id/input_language[text]None[enabled,,]",
      "view_str": "f1c958b80122fecde2035ade9a094c5e"
    },
    {
      "package": "com.traveloka.android",
      "visible": true,
      "checkable": false,
      "child_count": 0,
      "editable": false,
      "clickable": false,
      "is_password": false,
      "focusable": false,
      "enabled": true,
      "content_description": null,
      "children": [],
      "focused": false,
      "bounds": [
        [
          42,
          998
        ],
        [
          1038,
          1070
        ]
      ],
      "resource_id": "com.traveloka.android:id/label_text_view",
      "checked": false,
      "text": "Your Preferred Language",
      "class": "android.widget.TextView",
      "scrollable": false,
      "selected": false,
      "long_clickable": false,
      "parent": 23,
      "temp_id": 24,
      "size": "996*72",
      "signature": "[class]android.widget.TextView[resource_id]com.traveloka.android:id/label_text_view[text]Your Preferred Language[enabled,,]",
      "view_str": "83af9e34e4f79d2f193599f6f5200579",
      "allowed_actions": [
        "touch"
      ],
      "special_attrs": [],
      "local_id": "4",
      "desc": "<p bound_box=42,998,1038,1070>Your Preferred Language</p>"
    },
    {
      "package": "com.traveloka.android",
      "visible": true,
      "checkable": false,
      "child_count": 1,
      "editable": false,
      "clickable": false,
      "is_password": false,
      "focusable": false,
      "enabled": true,
      "content_description": null,
      "children": [
        26
      ],
      "focused": false,
      "bounds": [
        [
          42,
          1064
        ],
        [
          1038,
          1169
        ]
      ],
      "resource_id": "com.traveloka.android:id/widget_view",
      "checked": false,
      "text": null,
      "class": "android.widget.FrameLayout",
      "scrollable": false,
      "selected": false,
      "long_clickable": false,
      "parent": 23,
      "temp_id": 25,
      "size": "996*105",
      "signature": "[class]android.widget.FrameLayout[resource_id]com.traveloka.android:id/widget_view[text]None[enabled,,]",
      "view_str": "a68391dd9790dba4c54b8ff72c00ebfe"
    },
    {
      "package": "com.traveloka.android",
      "visible": true,
      "checkable": false,
      "child_count": 0,
      "editable": true,
      "clickable": true,
      "is_password": false,
      "focusable": true,
      "enabled": true,
      "content_description": null,
      "children": [],
      "focused": false,
      "bounds": [
        [
          42,
          1064
        ],
        [
          1038,
          1169
        ]
      ],
      "resource_id": "com.traveloka.android:id/edit_text_field",
      "checked": false,
      "text": "English",
      "class": "android.widget.EditText",
      "scrollable": false,
      "selected": false,
      "long_clickable": true,
      "parent": 25,
      "temp_id": 26,
      "size": "996*105",
      "signature": "[class]android.widget.EditText[resource_id]com.traveloka.android:id/edit_text_field[text]English[enabled,,]",
      "view_str": "b578c408260aa497512ab9007aa1a377",
      "allowed_actions": [
        "touch",
        "set_text",
        "long_touch"
      ],
      "special_attrs": [],
      "local_id": "5",
      "desc": "<input bound_box=42,1064,1038,1169>English</input>"
    },
    {
      "package": "com.traveloka.android",
      "visible": true,
      "checkable": false,
      "child_count": 0,
      "editable": false,
      "clickable": false,
      "is_password": false,
      "focusable": false,
      "enabled": true,
      "content_description": null,
      "children": [],
      "focused": false,
      "bounds": [
        [
          975,
          1096
        ],
        [
          1017,
          1138
        ]
      ],
      "resource_id": "com.traveloka.android:id/icon_end_view",
      "checked": false,
      "text": null,
      "class": "android.widget.ImageView",
      "scrollable": false,
      "selected": false,
      "long_clickable": false,
      "parent": 23,
      "temp_id": 27,
      "size": "42*42",
      "signature": "[class]android.widget.ImageView[resource_id]com.traveloka.android:id/icon_end_view[text]None[enabled,,]",
      "view_str": "f8693629137a1a4e288a29cd2e3e9529"
    },
    {
      "package": "com.traveloka.android",
      "visible": true,
      "checkable": false,
      "child_count": 2,
      "editable": false,
      "clickable": false,
      "is_password": false,
      "focusable": false,
      "enabled": true,
      "content_description": null,
      "children": [
        29,
        30
      ],
      "focused": false,
      "bounds": [
        [
          0,
          2085
        ],
        [
          1080,
          2274
        ]
      ],
      "resource_id": "com.traveloka.android:id/layout_continue",
      "checked": false,
      "text": null,
      "class": "android.widget.FrameLayout",
      "scrollable": false,
      "selected": false,
      "long_clickable": false,
      "parent": 11,
      "temp_id": 28,
      "size": "1080*189",
      "signature": "[class]android.widget.FrameLayout[resource_id]com.traveloka.android:id/layout_continue[text]None[enabled,,]",
      "view_str": "b9fffea359a59fb6dac43b8ca621a99e"
    },
    {
      "package": "com.traveloka.android",
      "visible": true,
      "checkable": false,
      "child_count": 0,
      "editable": false,
      "clickable": false,
      "is_password": false,
      "focusable": false,
      "enabled": true,
      "content_description": null,
      "children": [],
      "focused": false,
      "bounds": [
        [
          0,
          2085
        ],
        [
          1080,
          2088
        ]
      ],
      "resource_id": null,
      "checked": false,
      "text": null,
      "class": "android.view.View",
      "scrollable": false,
      "selected": false,
      "long_clickable": false,
      "parent": 28,
      "temp_id": 29,
      "size": "1080*3",
      "signature": "[class]android.view.View[resource_id]None[text]None[enabled,,]",
      "view_str": "0f89383f7291cccbb45179ad18b9c2c1"
    },
    {
      "package": "com.traveloka.android",
      "visible": true,
      "checkable": false,
      "child_count": 0,
      "editable": false,
      "clickable": true,
      "is_password": false,
      "focusable": true,
      "enabled": true,
      "content_description": null,
      "children": [],
      "focused": false,
      "bounds": [
        [
          42,
          2127
        ],
        [
          1038,
          2232
        ]
      ],
      "resource_id": "com.traveloka.android:id/on_board_button_continue",
      "checked": false,
      "text": "Continue",
      "class": "android.widget.Button",
      "scrollable": false,
      "selected": false,
      "long_clickable": false,
      "parent": 28,
      "temp_id": 30,
      "size": "996*105",
      "signature": "[class]android.widget.Button[resource_id]com.traveloka.android:id/on_board_button_continue[text]Continue[enabled,,]",
      "view_str": "18065bf07754a6f1d57b4d1544dcc38e",
      "allowed_actions": [
        "touch"
      ],
      "special_attrs": [],
      "local_id": "6",
      "desc": "<button bound_box=42,2127,1038,2232>Continue</button>"
    },
    {
      "package": "com.traveloka.android",
      "visible": false,
      "checkable": false,
      "child_count": 1,
      "editable": false,
      "clickable": false,
      "is_password": false,
      "focusable": false,
      "enabled": true,
      "content_description": null,
      "children": [
        32
      ],
      "focused": false,
      "bounds": [
        [
          1080,
          0
        ],
        [
          1080,
          2274
        ]
      ],
      "resource_id": "com.traveloka.android:id/postLocaleSelectionWidget",
      "checked": false,
      "text": null,
      "class": "android.widget.FrameLayout",
      "scrollable": false,
      "selected": false,
      "long_clickable": false,
      "parent": 9,
      "temp_id": 31,
      "size": "0*2274",
      "signature": "[class]android.widget.FrameLayout[resource_id]com.traveloka.android:id/postLocaleSelectionWidget[text]None[enabled,,]",
      "view_str": "8a59b385994565452534ede210adbb54"
    },
    {
      "package": "com.traveloka.android",
      "visible": false,
      "checkable": false,
      "child_count": 4,
      "editable": false,
      "clickable": false,
      "is_password": false,
      "focusable": false,
      "enabled": true,
      "content_description": null,
      "children": [
        33,
        34,
        35,
        36
      ],
      "focused": false,
      "bounds": [
        [
          1080,
          0
        ],
        [
          1080,
          2274
        ]
      ],
      "resource_id": null,
      "checked": false,
      "text": null,
      "class": "android.view.ViewGroup",
      "scrollable": false,
      "selected": false,
      "long_clickable": false,
      "parent": 31,
      "temp_id": 32,
      "size": "0*2274",
      "signature": "[class]android.view.ViewGroup[resource_id]None[text]None[enabled,,]",
      "view_str": "7dd29038ad1fd4395cf91801d5b135cf"
    },
    {
      "package": "com.traveloka.android",
      "visible": false,
      "checkable": false,
      "child_count": 0,
      "editable": false,
      "clickable": false,
      "is_password": false,
      "focusable": true,
      "enabled": true,
      "content_description": null,
      "children": [],
      "focused": false,
      "bounds": [
        [
          1080,
          0
        ],
        [
          1080,
          2147
        ]
      ],
      "resource_id": "com.traveloka.android:id/view_pager",
      "checked": false,
      "text": null,
      "class": "androidx.viewpager.widget.ViewPager",
      "scrollable": false,
      "selected": false,
      "long_clickable": false,
      "parent": 32,
      "temp_id": 33,
      "size": "0*2147",
      "signature": "[class]androidx.viewpager.widget.ViewPager[resource_id]com.traveloka.android:id/view_pager[text]None[enabled,,]",
      "view_str": "307c53dcc8c86a1824e0ab23832a6ee7"
    },
    {
      "package": "com.traveloka.android",
      "visible": false,
      "checkable": false,
      "child_count": 0,
      "editable": false,
      "clickable": true,
      "is_password": false,
      "focusable": true,
      "enabled": true,
      "content_description": null,
      "children": [],
      "focused": false,
      "bounds": [
        [
          1080,
          1974
        ],
        [
          1080,
          2274
        ]
      ],
      "resource_id": "com.traveloka.android:id/text_skip",
      "checked": false,
      "text": "Skip",
      "class": "android.widget.Button",
      "scrollable": false,
      "selected": false,
      "long_clickable": false,
      "parent": 32,
      "temp_id": 34,
      "size": "0*300",
      "signature": "[class]android.widget.Button[resource_id]com.traveloka.android:id/text_skip[text]Skip[enabled,,]",
      "view_str": "ffa21068d7da7e86f76c8070e154e689"
    },
    {
      "package": "com.traveloka.android",
      "visible": false,
      "checkable": false,
      "child_count": 0,
      "editable": false,
      "clickable": true,
      "is_password": false,
      "focusable": true,
      "enabled": true,
      "content_description": null,
      "children": [],
      "focused": false,
      "bounds": [
        [
          1080,
          1974
        ],
        [
          1080,
          2274
        ]
      ],
      "resource_id": "com.traveloka.android:id/text_next",
      "checked": false,
      "text": "Next",
      "class": "android.widget.Button",
      "scrollable": false,
      "selected": false,
      "long_clickable": false,
      "parent": 32,
      "temp_id": 35,
      "size": "0*300",
      "signature": "[class]android.widget.Button[resource_id]com.traveloka.android:id/text_next[text]Next[enabled,,]",
      "view_str": "5c44eef97d11c7562cf57628a801d69b"
    },
    {
      "package": "com.traveloka.android",
      "visible": false,
      "checkable": false,
      "child_count": 0,
      "editable": false,
      "clickable": false,
      "is_password": false,
      "focusable": false,
      "enabled": true,
      "content_description": null,
      "children": [],
      "focused": false,
      "bounds": [
        [
          1122,
          2189
        ],
        [
          1080,
          2211
        ]
      ],
      "resource_id": "com.traveloka.android:id/pager_indicator",
      "checked": false,
      "text": null,
      "class": "android.view.View",
      "scrollable": false,
      "selected": false,
      "long_clickable": false,
      "parent": 32,
      "temp_id": 36,
      "size": "-42*22",
      "signature": "[class]android.view.View[resource_id]com.traveloka.android:id/pager_indicator[text]None[enabled,,]",
      "view_str": "1d96f04bc1361302d776d66ab75e88b9"
    },
    {
      "package": "com.traveloka.android",
      "visible": false,
      "checkable": false,
      "child_count": 1,
      "editable": false,
      "clickable": false,
      "is_password": false,
      "focusable": false,
      "enabled": true,
      "content_description": null,
      "children": [
        38
      ],
      "focused": false,
      "bounds": [
        [
          0,
          0
        ],
        [
          1080,
          2274
        ]
      ],
      "resource_id": "com.traveloka.android:id/widget_waiting",
      "checked": false,
      "text": null,
      "class": "android.widget.RelativeLayout",
      "scrollable": false,
      "selected": false,
      "long_clickable": false,
      "parent": 8,
      "temp_id": 37,
      "size": "1080*2274",
      "signature": "[class]android.widget.RelativeLayout[resource_id]com.traveloka.android:id/widget_waiting[text]None[enabled,,]",
      "view_str": "71d339160bfbadbf5848cef8e2c07c43"
    },
    {
      "package": "com.traveloka.android",
      "visible": false,
      "checkable": false,
      "child_count": 2,
      "editable": false,
      "clickable": false,
      "is_password": false,
      "focusable": false,
      "enabled": true,
      "content_description": null,
      "children": [
        39,
        41
      ],
      "focused": false,
      "bounds": [
        [
          0,
          0
        ],
        [
          1080,
          2274
        ]
      ],
      "resource_id": null,
      "checked": false,
      "text": null,
      "class": "android.widget.LinearLayout",
      "scrollable": false,
      "selected": false,
      "long_clickable": false,
      "parent": 37,
      "temp_id": 38,
      "size": "1080*2274",
      "signature": "[class]android.widget.LinearLayout[resource_id]None[text]None[enabled,,]",
      "view_str": "49c96b875a88555e4f3bd0d56cb4bae1"
    },
    {
      "package": "com.traveloka.android",
      "visible": false,
      "checkable": false,
      "child_count": 1,
      "editable": false,
      "clickable": false,
      "is_password": false,
      "focusable": false,
      "enabled": true,
      "content_description": null,
      "children": [
        40
      ],
      "focused": false,
      "bounds": [
        [
          0,
          0
        ],
        [
          1080,
          1137
        ]
      ],
      "resource_id": null,
      "checked": false,
      "text": null,
      "class": "android.widget.RelativeLayout",
      "scrollable": false,
      "selected": false,
      "long_clickable": false,
      "parent": 38,
      "temp_id": 39,
      "size": "1080*1137",
      "signature": "[class]android.widget.RelativeLayout[resource_id]None[text]None[enabled,,]",
      "view_str": "f972cc149fafd93edda9e91cc6cdf1db"
    },
    {
      "package": "com.traveloka.android",
      "visible": false,
      "checkable": false,
      "child_count": 0,
      "editable": false,
      "clickable": false,
      "is_password": false,
      "focusable": false,
      "enabled": true,
      "content_description": null,
      "children": [],
      "focused": false,
      "bounds": [
        [
          382,
          210
        ],
        [
          697,
          525
        ]
      ],
      "resource_id": "com.traveloka.android:id/image_view_logo",
      "checked": false,
      "text": null,
      "class": "android.widget.ImageView",
      "scrollable": false,
      "selected": false,
      "long_clickable": false,
      "parent": 39,
      "temp_id": 40,
      "size": "315*315",
      "signature": "[class]android.widget.ImageView[resource_id]com.traveloka.android:id/image_view_logo[text]None[enabled,,]",
      "view_str": "472c18bfa95e8638dfba4d87a4f2ffcd"
    },
    {
      "package": "com.traveloka.android",
      "visible": false,
      "checkable": false,
      "child_count": 2,
      "editable": false,
      "clickable": false,
      "is_password": false,
      "focusable": false,
      "enabled": true,
      "content_description": null,
      "children": [
        42,
        43
      ],
      "focused": false,
      "bounds": [
        [
          0,
          1137
        ],
        [
          1080,
          2274
        ]
      ],
      "resource_id": null,
      "checked": false,
      "text": null,
      "class": "android.widget.LinearLayout",
      "scrollable": false,
      "selected": false,
      "long_clickable": false,
      "parent": 38,
      "temp_id": 41,
      "size": "1080*1137",
      "signature": "[class]android.widget.LinearLayout[resource_id]None[text]None[enabled,,]",
      "view_str": "ce24babcec2467a8c3eeccd8298c85d8"
    },
    {
      "package": "com.traveloka.android",
      "visible": false,
      "checkable": false,
      "child_count": 0,
      "editable": false,
      "clickable": false,
      "is_password": false,
      "focusable": false,
      "enabled": true,
      "content_description": null,
      "children": [],
      "focused": false,
      "bounds": [
        [
          0,
          1137
        ],
        [
          1080,
          1200
        ]
      ],
      "resource_id": "com.traveloka.android:id/text_view_waiting_title",
      "checked": false,
      "text": "Please wait, currently transferring your data",
      "class": "android.widget.TextView",
      "scrollable": false,
      "selected": false,
      "long_clickable": false,
      "parent": 41,
      "temp_id": 42,
      "size": "1080*63",
      "signature": "[class]android.widget.TextView[resource_id]com.traveloka.android:id/text_view_waiting_title[text]Please wait, currently transferring your data[enabled,,]",
      "view_str": "cb6330d19fd6e51cedb8af3a0dee4f55"
    },
    {
      "package": "com.traveloka.android",
      "visible": false,
      "checkable": false,
      "child_count": 0,
      "editable": false,
      "clickable": false,
      "is_password": false,
      "focusable": false,
      "enabled": true,
      "content_description": null,
      "children": [],
      "focused": false,
      "bounds": [
        [
          0,
          1305
        ],
        [
          1080,
          1409
        ]
      ],
      "resource_id": "com.traveloka.android:id/text_view_waiting_content",
      "checked": false,
      "text": "Do not exit the application, this will only take\nless than a minute.",
      "class": "android.widget.TextView",
      "scrollable": false,
      "selected": false,
      "long_clickable": false,
      "parent": 41,
      "temp_id": 43,
      "size": "1080*104",
      "signature": "[class]android.widget.TextView[resource_id]com.traveloka.android:id/text_view_waiting_content[text]None[enabled,,]",
      "view_str": "6549a4a2978a9ea6a68482a37152597f"
    },
    {
      "package": "com.traveloka.android",
      "visible": false,
      "checkable": false,
      "child_count": 0,
      "editable": false,
      "clickable": false,
      "is_password": false,
      "focusable": false,
      "enabled": true,
      "content_description": null,
      "children": [],
      "focused": false,
      "bounds": [
        [
          0,
          2274
        ],
        [
          1080,
          2400
        ]
      ],
      "resource_id": "android:id/navigationBarBackground",
      "checked": false,
      "text": null,
      "class": "android.view.View",
      "scrollable": false,
      "selected": false,
      "long_clickable": false,
      "parent": 0,
      "temp_id": 44,
      "size": "1080*126",
      "signature": "[class]android.view.View[resource_id]android:id/navigationBarBackground[text]None[enabled,,]",
      "view_str": "ef8770529334cd86a98a8773c4c7e527"
    }
  ]
}